cdds/__init__.py
cdds/cdds.py
cdds/cli.py
cdds/datasets.py
cdds/imports.py
cdds/inspect.py
cdds/lp_functions.py
cdds/lp_style.py
cdds/utils.py
cdds-1.1.1.dist-info/AUTHORS.rst
cdds-1.1.1.dist-info/METADATA
cdds-1.1.1.dist-info/WHEEL
cdds-1.1.1.dist-info/entry_points.txt
cdds-1.1.1.dist-info/top_level.txt
cdds-1.1.1.dist-info/RECORD
